{"is_source_file": true, "format": "JavaScript", "description": "This file generates an OpenAPI specification file ('openapi.json') from a Swagger specification object by writing it to a specified directory.", "external_files": ["./swagger"], "external_methods": ["fs.existsSync", "fs.mkdirSync", "fs.writeFileSync"], "published": [], "classes": [], "methods": [], "calls": ["fs.existsSync", "fs.mkdirSync", "fs.writeFileSync"], "search-terms": ["generate_openapi.js", "swaggerSpec", "openapi.json", "writeFileSync", "directory creation", "Swagger"], "state": 2, "file_id": 11, "knowledge_revision": 24, "git_revision": "8e9e262a8719f40ebe4b046b39b41255e8ccaaaa", "ctags": [{"_type": "tag", "name": "fs", "path": "/home/kavia/workspace/code-generation/online-grocery-mart-19003-19047/DiscountService/generate_openapi.js", "pattern": "/^const fs = require('fs');$/", "language": "JavaScript", "kind": "constant"}, {"_type": "tag", "name": "outputDir", "path": "/home/kavia/workspace/code-generation/online-grocery-mart-19003-19047/DiscountService/generate_openapi.js", "pattern": "/^const outputDir = path.join(__dirname, 'interfaces');$/", "language": "JavaScript", "kind": "constant"}, {"_type": "tag", "name": "outputPath", "path": "/home/kavia/workspace/code-generation/online-grocery-mart-19003-19047/DiscountService/generate_openapi.js", "pattern": "/^const outputPath = path.join(outputDir, 'openapi.json');$/", "language": "JavaScript", "kind": "constant"}, {"_type": "tag", "name": "path", "path": "/home/kavia/workspace/code-generation/online-grocery-mart-19003-19047/DiscountService/generate_openapi.js", "pattern": "/^const path = require('path');$/", "language": "JavaScript", "kind": "constant"}, {"_type": "tag", "name": "swaggerSpec", "path": "/home/kavia/workspace/code-generation/online-grocery-mart-19003-19047/DiscountService/generate_openapi.js", "pattern": "/^const swaggerSpec = require('.\\/swagger');$/", "language": "JavaScript", "kind": "constant"}], "hash": "55a8452439ff8971a692025b12dc20dc", "format-version": 4, "code-base-name": "DiscountService", "filename": "DiscountService/generate_openapi.js", "revision_history": [{"24": "8e9e262a8719f40ebe4b046b39b41255e8ccaaaa"}]}